{
  "format_version": "2.0.0",
  "rows": [
    {
      "accounts_payable_account_id": 2,
      "accounts_receivable_account_id": 1,
      "default_cheque_credit_account_id": 8,
      "default_cheque_debit_account_id": 17,
      "id": 1,
      "max_attachment_upload_bytes": 5242880,
      "max_cheque_series_count": 60,
      "prepaid_expenses_account_id": 4,
      "unallocated_credits_account_id": 5,
      "unallocated_debits_account_id": 6,
      "unearned_revenue_account_id": 3,
      "updated_at": "2026-05-01T00:00:00-04:00"
    }
  ],
  "table": "ledger_settings"
}
